wxconv/__init__.py
wxconv/__main__.py
wxconv/mapping/norm_urd.map
wxconv/mapping/urd-wx.map
wxconv/mapping/wx-urd.map
wxconv/ssf_reader.py
wxconv/tests/__init__.py
wxconv/tests/conll/hin.conll
wxconv/tests/plain_text/ben.txt
wxconv/tests/plain_text/guj.txt
wxconv/tests/plain_text/hin.txt
wxconv/tests/plain_text/kan.txt
wxconv/tests/plain_text/mal.txt
wxconv/tests/plain_text/ori.txt
wxconv/tests/plain_text/pan.txt
wxconv/tests/plain_text/tam.txt
wxconv/tests/plain_text/tel.txt
wxconv/tests/plain_text/urd.txt
wxconv/tests/ssf/hin.ssf
wxconv/tests/test_wxconv.py
wxconv/tests/tnt/hin.tnt
wxconv/wx.py
wxconv/wx_format.py
wxconv-1.0.0.0.dist-info/entry_points.txt
wxconv-1.0.0.0.dist-info/LICENSE.md
wxconv-1.0.0.0.dist-info/WHEEL
wxconv-1.0.0.0.dist-info/METADATA
wxconv-1.0.0.0.dist-info/RECORD
